{
    "description": "IBM WAS Liberty Kernel",
    "homepage": "https://developer.ibm.com/wasdev/websphere-liberty/",
    "license": "https://public.dhe.ibm.com/ibmdl/export/pub/software/websphere/wasdev/downloads/wlp/19.0.0.7/lafiles/runtime/en.html",
    "version": "19.0.0.7",
    "url": "https://public.dhe.ibm.com/ibmdl/export/pub/software/websphere/wasdev/downloads/wlp/19.0.0.7/wlp-kernel-19.0.0.7.zip",
    "hash": "c390823b834d6957d30cc9d5630fe2f8513dc3b20f67db78edefc8943b2ecda8",
    "extract_dir": "wlp",
    "bin": [
        "bin\\binaryLog.bat",
        "bin\\configUtility.bat",
        "bin\\featureManager.bat",
        "bin\\installUtility.bat",
        "bin\\productInfo.bat",
        "bin\\securityUtility.bat",
        [
            "bin\\server.bat",
            "wlp"
        ],
        "bin\\serverSchemaGen.bat"
    ],
    "persist": "usr",
    "checkver": {
        "url": "https://public.dhe.ibm.com/ibmdl/export/pub/software/websphere/wasdev/downloads/wlp/",
        "re": "([\\d]{2}.[\\d.]+)/",
        "reverse": true
    },
    "autoupdate": {
        "url": "https://public.dhe.ibm.com/ibmdl/export/pub/software/websphere/wasdev/downloads/wlp/$version/wlp-kernel-$version.zip",
        "license": "https://public.dhe.ibm.com/ibmdl/export/pub/software/websphere/wasdev/downloads/wlp/$version/lafiles/runtime/en.html"
    },
    "notes": "server.bat is renamed to wlp"
}
